moretypeops/__init__.py
moretypeops-1.0.3.dist-info/LICENSE
moretypeops-1.0.3.dist-info/METADATA
moretypeops-1.0.3.dist-info/WHEEL
moretypeops-1.0.3.dist-info/top_level.txt
moretypeops-1.0.3.dist-info/RECORD
