Metadata-Version: 2.1
Name: moretypeops
Version: 1.0.3
Summary: More useful functions for operators when working with data types
Author-email: Nguyen Minh Khoi <khoi.nguyenminh100912@gmail.com>
Project-URL: Homepage, https://github.com/pypa/moretypeops
Project-URL: Issues, https://github.com/pypa/moretypeops/issues
Classifier: Programming Language :: Python :: 3
Classifier: License :: OSI Approved :: MIT License
Classifier: Operating System :: OS Independent
Requires-Python: >=3
License-File: LICENSE
